setup.py
smr/__init__.py
smr/config.py
smr/ec2.py
smr/main.py
smr/map.py
smr/reduce.py
smr/shared.py
smr/uri.py
smr/version.py
smr.egg-info/PKG-INFO
smr.egg-info/SOURCES.txt
smr.egg-info/dependency_links.txt
smr.egg-info/entry_points.txt
smr.egg-info/requires.txt
smr.egg-info/top_level.txt
test/test_uri.py