Metadata-Version: 1.0
Name: smr
Version: 0.0.3
Summary: SMR (Simple Map Reduce) is a simple tool for writing map-reduce jobs in python
Home-page: https://github.com/idyedov/smr
Author: Ivan Dyedov
Author-email: ivan@dyedov.com
License: UNKNOWN
Platform: UNKNOWN
